DiffusersServer/Pipelines.py
DiffusersServer/VideoPipelines.py
DiffusersServer/__init__.py
DiffusersServer/create_server.py
DiffusersServer/server.py
DiffusersServer/waitress_server.py
diffusersserver-0.1.40.dist-info/METADATA
diffusersserver-0.1.40.dist-info/WHEEL
diffusersserver-0.1.40.dist-info/RECORD
