Metadata-Version: 2.4
Name: DiffusersServer
Version: 0.1.40
Summary: Nueva solución tipo Ollama pero para modelos de Text2Img
Author-email: "Rivera.ai/Fredy Rivera" <riveraaai200678@gmail.com>
Requires-Python: >=3.8
Requires-Dist: diffusers
Requires-Dist: flask
Requires-Dist: flask-cors
Requires-Dist: psutil
Requires-Dist: sentencepiece
Requires-Dist: torch
Requires-Dist: torchvision
Requires-Dist: transformers==4.49.0
Requires-Dist: waitress
